{"version":1,"resource":"file:///home/justin/.cspell/custom-dictionary-user.txt","entries":[{"id":"Khjo.txt","source":"Workspace Edit","timestamp":1732767957139},{"id":"8V8d.txt","source":"Workspace Edit","timestamp":1732767969069},{"id":"fzYI.txt","source":"Workspace Edit","timestamp":1732768044614},{"id":"8jPL.txt","source":"Workspace Edit","timestamp":1732850083686},{"id":"5kfQ.txt","source":"Workspace Edit","timestamp":1733184722948},{"id":"xLsZ.txt","source":"Workspace Edit","timestamp":1733339435413}]}